olx_db/__init__.py
olx_db/config.py
olx_db/version.py
olx_db/db/__init__.py
olx_db/db/database.py
olx_db/db/__pycache__/__init__.cpython-313.pyc
olx_db/db/__pycache__/database.cpython-313.pyc
olx_db_wonsky-1.1.8.dist-info/licenses/LICENSE
olx_db_wonsky-1.1.8.dist-info/METADATA
olx_db_wonsky-1.1.8.dist-info/WHEEL
olx_db_wonsky-1.1.8.dist-info/top_level.txt
olx_db_wonsky-1.1.8.dist-info/RECORD
