Metadata-Version: 2.4
Name: olx-db-wonsky
Version: 1.1.8
Summary: OLX database models and migrations
Author: Wonsky
Author-email: Vladyslav <vladyslav.pidborskyi@gmail.com>
Project-URL: Homepage, https://github.com/yourusername/olx-db
Project-URL: Bug Tracker, https://github.com/yourusername/olx-db/issues
Classifier: Programming Language :: Python :: 3
Classifier: License :: OSI Approved :: MIT License
Classifier: Operating System :: OS Independent
Requires-Python: >=3.7
License-File: LICENSE
Requires-Dist: sqlalchemy
Requires-Dist: pytz
Requires-Dist: python-dotenv
Requires-Dist: psycopg2-binary
Dynamic: author
Dynamic: license-file
Dynamic: requires-python
